Metadata-Version: 1.1
Name: srinivascalculator
Version: 0.1.3
Summary: A very basic calculator
Home-page: https://github.com/srsapireddy
Author: Sapireddy Srinivas Rahul
Author-email: sapireddyrahul@gmail.com
License: MIT
Keywords: calculator
Platform: UNKNOWN
Classifier: Development Status :: 5 - Production/Stable
Classifier: Intended Audience :: Education
Classifier: Operating System :: Microsoft :: Windows :: Windows 10
Classifier: License :: OSI Approved :: MIT License
Classifier: Programming Language :: Python :: 3
